[
  {
    "name": "Jeu de l'oie",
    "teaser": "Légendaire premier plateau du BDSM.",
    "description": "Petit nouveau 3a dans ton école préféré, Polytech Nice, vit ou revit les 3 années de cursus ingénieur les plus folles du réseau. Tu retrouveras tous les plus grands événements de ton cursus !",
    "imgUrl": "assets/icons/goose.svg",
    "chips": [
      "Hard",
      "Danger"
    ],
    "cells": [
    ],
    "date": 1612209433,
    "event": true,
    "screenshots": [
      "screen1.png",
      "screen2.png"
    ]
  },
  {
    "name": "Hénéken",
    "teaser": "Pour passer une petite soirée, entre amis tranquille. Ca sera le feu !",
    "description": "Tu veux commencer P'tit godet en étant sûr de t'en sortir en un seul morceau ? Hénéken est sûrement le bon choix. Mais ne te plains pas de ne pas t'être assez amusé après !",
    "imgUrl": "https://pbs.twimg.com/profile_images/2517626038/h8qq4gtkn20v6j9zl2lp_400x400.jpeg",
    "cells": [],
    "date": 1612209431,
    "event": false,
    "chips": [
      "Bière",
      "Facile"
    ],
    "screenshots": [
      "screen1.png",
      "screen2.png"
    ]
  },
  {
    "name": "Example",
    "teaser": "Pour passer une petite soirée, entre amis tranquille. Ca sera le feu !",
    "description": "Tu veux commencer P'tit godet en étant sûr de t'en sortir en un seul morceau ? Hénéken est sûrement le bon choix. Mais ne te plains pas de ne pas t'être assez amusé après !",
    "imgUrl": "assets/icons/beer.svg",
    "cells": [],
    "date": 1612209431,
    "event": false,
    "chips": [
      "Bière",
      "Facile"
    ],
    "screenshots": [
      "screen1.png",
      "screen2.png"
    ]
  },
  {
    "name": "Test 2345",
    "teaser": "Pour passer une petite soirée, entre amis tranquille. Ca sera le feu !",
    "description": "Tu veux commencer P'tit godet en étant sûr de t'en sortir en un seul morceau ? Hénéken est sûrement le bon choix. Mais ne te plains pas de ne pas t'être assez amusé après !",
    "imgUrl": "assets/icons/goose.svg",
    "cells": [],
    "date": 1612209431,
    "event": false,
    "chips": [
      "Bière",
      "Facile"
    ],
    "screenshots": [
      "screen1.png",
      "screen2.png"
    ]
  },
  {
    "name": "Prout",
    "teaser": "Pour passer une petite soirée, entre amis tranquille. Ca sera le feu !",
    "description": "Tu veux commencer P'tit godet en étant sûr de t'en sortir en un seul morceau ? Hénéken est sûrement le bon choix. Mais ne te plains pas de ne pas t'être assez amusé après !",
    "imgUrl": "https://pbs.twimg.com/profile_images/2517626038/h8qq4gtkn20v6j9zl2lp_400x400.jpeg",
    "cells": [],
    "date": 1612209431,
    "event": false,
    "chips": [
      "Bière",
      "Facile"
    ],
    "screenshots": [
      "screen1.png",
      "screen2.png"
    ]
  },
  {
    "name": "Enfin fréro",
    "teaser": "Pour passer une petite soirée, entre amis tranquille. Ca sera le feu !",
    "description": "Tu veux commencer P'tit godet en étant sûr de t'en sortir en un seul morceau ? Hénéken est sûrement le bon choix. Mais ne te plains pas de ne pas t'être assez amusé après !",
    "imgUrl": "assets/icons/beer.svg",
    "cells": [],
    "date": 1612209431,
    "event": false,
    "chips": [
      "Bière",
      "Facile"
    ],
    "screenshots": [
      "screen1.png",
      "screen2.png"
    ]
  }
]